pyratefacts/__init__.py
pyratefacts/artifacts/__init__.py
pyratefacts/artifacts/artifact.py
pyratefacts/artifacts/hash.py
pyratefacts/artifacts/ops.py
pyratefacts/artifacts/uncompress.py
pyratefacts/downloaders/__init__.py
pyratefacts/downloaders/http.py
pyratefacts/downloaders/local.py
pyratefacts/manager/__init__.py
pyratefacts/manager/datafile.py
pyratefacts/manager/manager.py
pyratefacts/parser/__init__.py
pyratefacts/parser/parser.py
pyratefacts-1.0.0.dist-info/METADATA
pyratefacts-1.0.0.dist-info/WHEEL
pyratefacts-1.0.0.dist-info/top_level.txt
pyratefacts-1.0.0.dist-info/RECORD
