Metadata-Version: 2.1
Name: pyratefacts
Version: 1.0.0
Summary: A simple module for loading artifacts from http or local and managing them
Home-page: https://github.com/fsan/pyratefacts
Author: fsan
Author-email: pabyo.sansinaeti@gmail.com
License: UNKNOWN
Download-URL: https://github.com/fsan/pyratefacts/releases/download/1.0.0/pyratefacts-1.0.0-py3-none-any.whl
Keywords: artifact management
Platform: UNKNOWN
Requires-Python: >=3.6
Requires-Dist: atomicwrites (==1.4.0)
Requires-Dist: attrs (==19.3.0)
Requires-Dist: certifi (==2020.4.5.1)
Requires-Dist: chardet (==3.0.4)
Requires-Dist: colorama (==0.4.3)
Requires-Dist: coverage (==5.1)
Requires-Dist: idna (==2.9)
Requires-Dist: importlib-metadata (==1.6.0)
Requires-Dist: more-itertools (==8.2.0)
Requires-Dist: packaging (==20.3)
Requires-Dist: pluggy (==0.13.1)
Requires-Dist: py (==1.8.1)
Requires-Dist: pyparsing (==2.4.7)
Requires-Dist: pyperaptor (==0.1.3.1)
Requires-Dist: pytest (==5.4.1)
Requires-Dist: pytest-cov (==2.8.1)
Requires-Dist: requests (==2.23.0)
Requires-Dist: six (==1.14.0)
Requires-Dist: urllib3 (==1.25.9)
Requires-Dist: wcwidth (==0.1.9)
Requires-Dist: zipp (==3.1.0)
